README.md
setup.py
servz/__init__.py
servz/main.py
servz.egg-info/PKG-INFO
servz.egg-info/SOURCES.txt
servz.egg-info/dependency_links.txt
servz.egg-info/top_level.txt
servz/core/__init__.py
servz/core/build_pipeline.py
servz/core/build_step.py
servz/core/builder.py
servz/core/director.py
servz/core/endpoint_appender/__init__.py
servz/core/endpoint_appender/endpoint_appender.py
servz/core/endpoint_appender/flask_appender.py
servz/core/orchestration_artifact_builder/__init__.py
servz/core/orchestration_artifact_builder/orchestration_artifact_builder.py
servz/core/orchestration_artifact_builder/prefect_artifact_builder.py
servz/core/package_publisher/__init__.py
servz/core/package_publisher/package_publisher.py
servz/core/package_publisher/zipfile_publisher.py
servz/core/packager/__init__.py
servz/core/packager/packager.py
servz/core/packager/prefect_file_packager.py
servz/core/pipline_composer/__init__.py
servz/core/pipline_composer/pipeline_composer.py
servz/core/pipline_composer/yaml_pipeline_composer.py
servz/core/workflow_validator/__init__.py
servz/core/workflow_validator/workflow_validator.py
servz/core/workflow_validator/yaml_validator.py
servz/templates/prefect_templates/prefect_class_template
servz/templates/prefect_templates/prefect_edge_template
servz/templates/prefect_templates/prefect_flow_template
servz/templates/prefect_templates/prefect_instance_template
servz/templates/server_templates/flask/app
servz/utils/__init__.py
servz/utils/exceptions/__init__.py
servz/utils/exceptions/container_build_error.py
servz/utils/exceptions/deploy_script_generation_error.py
servz/utils/exceptions/docker_file_create_error.py
servz/utils/exceptions/flow_build_error.py
servz/utils/exceptions/flow_validation_error.py
servz/utils/exceptions/ml_error.py
servz/utils/exceptions/orchestration_artifact_build_error.py
servz/utils/exceptions/packager_error.py
servz/utils/exceptions/pipeline_read_error.py
servz/utils/parsers/__init__.py
servz/utils/parsers/cmd_config_parser.py
servz/utils/parsers/config_parser.py
servz/utils/parsers/parser.py
servz/utils/parsers/project_config.py
